triq/__init__.py
triq/qt.py
triq/triq.py
triq-0.0.4.dist-info/LICENSE
triq-0.0.4.dist-info/METADATA
triq-0.0.4.dist-info/WHEEL
triq-0.0.4.dist-info/top_level.txt
triq-0.0.4.dist-info/RECORD
