Metadata-Version: 2.1
Name: triq
Version: 0.0.4
Summary: Use trio async framework with PySide2/PyQt5
Home-page: https://github.com/innodatalabs/triq/
Author: Mike Kroutikov
Author-email: mkroutikov@innodata.com
License: MIT
Keywords: pyqt pyside async trio
Platform: UNKNOWN
Classifier: Development Status :: 3 - Alpha
Classifier: Intended Audience :: Developers
Classifier: Programming Language :: Python :: 3.6
Classifier: Programming Language :: Python :: 3.7
Classifier: Programming Language :: Python :: 3.8
Classifier: Programming Language :: Python :: Implementation :: CPython
Classifier: Programming Language :: Python :: Implementation :: PyPy
Classifier: Topic :: Software Development :: Libraries :: Python Modules
Requires-Dist: trio (~=0.16.0)
